wexample_file-0.0.52.dist-info/METADATA
wexample_file-0.0.52.dist-info/WHEEL
wexample_file-0.0.52.dist-info/entry_points.txt
wexample_file-0.0.52.dist-info/licenses/LICENSE
wexample_file/__init__.py
wexample_file/__pycache__/__init__.py
wexample_file/common/__init__.py
wexample_file/common/__pycache__/__init__.py
wexample_file/common/abstract_local_item_path.py
wexample_file/common/local_directory.py
wexample_file/common/local_file.py
wexample_file/enum/__init__.py
wexample_file/enum/__pycache__/__init__.py
wexample_file/enum/local_path_type.py
wexample_file/exception/__init__.py
wexample_file/exception/__pycache__/__init__.py
wexample_file/exception/directory_not_found_exception.py
wexample_file/exception/file_not_found_exception.py
wexample_file/exception/not_a_directory_exception.py
wexample_file/exception/not_a_file_exception.py
wexample_file/helper/__init__.py
wexample_file/helper/line.py
wexample_file/mixin/__init__.py
wexample_file/mixin/__pycache__/__init__.py
wexample_file/mixin/with_local_directory_mixin.py
wexample_file/mixin/with_local_file_mixin.py
wexample_file/py.typed
wexample_file-0.0.52.dist-info/RECORD
